EdaFirstPhase/eda.py
outliers_detection-0.12.dist-info/METADATA
outliers_detection-0.12.dist-info/WHEEL
outliers_detection-0.12.dist-info/top_level.txt
outliers_detection-0.12.dist-info/RECORD
