Metadata-Version: 2.1
Name: outliers-detection
Version: 0.12
Summary: Outlier Detection
Home-page: UNKNOWN
Author: Gaurav Srivastava
Author-email: gaurav0535@hotmail.com
License: MIT
Platform: UNKNOWN
